<?xml version="1.0" encoding="utf-8"?>
<ecommerce.couponcode>
  <CouponCodeCode>DGCOREU1O57</CouponCodeCode>
  <CouponCodeDiscountID>
    <CodeName>10_OffForTheFirstOrder</CodeName>
    <GUID>8abe626a-c8eb-4ad5-b887-1100c9a01b02</GUID>
    <ObjectType>ecommerce.discount</ObjectType>
    <Site>
      <CodeName>DancingGoatCore</CodeName>
      <GUID>1068a102-3f26-4a5f-833d-93efd0b18939</GUID>
      <ObjectType>cms.site</ObjectType>
    </Site>
  </CouponCodeDiscountID>
  <CouponCodeGUID>bdec9713-2ad3-4194-995d-284be4684ac0</CouponCodeGUID>
  <CouponCodeUseLimit>1</CouponCodeUseLimit>
</ecommerce.couponcode>